setup.py
src/buildout_starter.egg-info/PKG-INFO
src/buildout_starter.egg-info/SOURCES.txt
src/buildout_starter.egg-info/dependency_links.txt
src/buildout_starter.egg-info/entry_points.txt
src/buildout_starter.egg-info/requires.txt
src/buildout_starter.egg-info/top_level.txt
src/buildout_starter.egg-info/zip-safe
src/buildoutstarter/__init__.py
src/buildoutstarter/config.py
src/buildoutstarter/templates.py