Metadata-Version: 1.0
Name: buildout-starter
Version: 0.1.0
Summary: A project creation utility for starting zc.buildout Python and Django projects.
Home-page: https://github.com/rfkrocktk/buildout-starter
Author: Naftuli Tzvi Kay
Author-email: naftulitzvikay@gmail.com
License: LGPL
Platform: UNKNOWN
